multi_agent_env/__init__.py
multi_agent_env/agent.py
multi_agent_env/env.py
multi_agent_env/renderer.py
multi_agent_env/utils.py
multi_agent_env-0.2.1.dist-info/LICENSE
multi_agent_env-0.2.1.dist-info/METADATA
multi_agent_env-0.2.1.dist-info/WHEEL
multi_agent_env-0.2.1.dist-info/top_level.txt
multi_agent_env-0.2.1.dist-info/RECORD
