Metadata-Version: 2.1
Name: multi-agent-env
Version: 0.2.1
Summary: Multi-agent environment for reinforcement learning
Home-page: https://github.com/ECE324-MI-Gang/Multi-agent-Env
Author: Ted
License: GPL-3.0
License-File: LICENSE
Requires-Dist: numpy
Requires-Dist: pygame
